finecode/__init__.py
finecode/__main__.py
finecode/_version.py
finecode/app_dirs.py
finecode/base_config.toml
finecode/cli.py
finecode/communication_utils.py
finecode/context.py
finecode/dirs_utils.py
finecode/domain.py
finecode/find_project.py
finecode/finecode_cmd.py
finecode/logger_utils.py
finecode/main.py
finecode/payload_preprocessor.py
finecode/project_analyzer.py
finecode/proxy_utils.py
finecode/py.typed
finecode/pygls_client_utils.py
finecode/pygls_server_utils.py
finecode/pygls_types_utils.py
finecode/services.py
finecode/user_messages.py
finecode/watch_and_run.py
finecode/watcher.py
finecode/cli_app/__init__.py
finecode/cli_app/dump_config.py
finecode/cli_app/prepare_envs.py
finecode/cli_app/run.py
finecode/config/__init__.py
finecode/config/collect_actions.py
finecode/config/config_models.py
finecode/config/read_configs.py
finecode/lsp_server/__init__.py
finecode/lsp_server/global_state.py
finecode/lsp_server/lsp_server.py
finecode/lsp_server/schemas.py
finecode/lsp_server/services.py
finecode/lsp_server/endpoints/__init__.py
finecode/lsp_server/endpoints/action_tree.py
finecode/lsp_server/endpoints/code_actions.py
finecode/lsp_server/endpoints/code_lens.py
finecode/lsp_server/endpoints/diagnostics.py
finecode/lsp_server/endpoints/document_sync.py
finecode/lsp_server/endpoints/formatting.py
finecode/lsp_server/endpoints/inlay_hints.py
finecode/runner/__init__.py
finecode/runner/manager.py
finecode/runner/runner_client.py
finecode/runner/runner_info.py
finecode/utils/__init__.py
finecode/utils/async_proc_queue.py
finecode/utils/iterable_subscribe.py
finecode-0.3.dist-info/licenses/LICENSE
finecode-0.3.dist-info/METADATA
finecode-0.3.dist-info/WHEEL
finecode-0.3.dist-info/top_level.txt
finecode-0.3.dist-info/RECORD
