Metadata-Version: 2.4
Name: finecode
Version: 0.3
Author-email: Vladyslav Hnatiuk <aders1234@gmail.com>
Requires-Python: <3.14,>=3.11
License-File: LICENSE
Requires-Dist: loguru==0.7.*
Requires-Dist: tomlkit==0.11.*
Requires-Dist: watchdog==4.0.*
Requires-Dist: click==8.1.*
Requires-Dist: pydantic==2.10.*
Requires-Dist: platformdirs==4.3.*
Requires-Dist: pygls==2.0.0-a2
Requires-Dist: finecode_extension_api==0.3.*
Requires-Dist: finecode_extension_runner==0.3.*
Requires-Dist: ordered-set==4.1.*
Requires-Dist: mcp==1.9.*
Requires-Dist: fine_python_virtualenv==0.1.*
Requires-Dist: fine_python_pip==0.1.*
Dynamic: license-file
